kaikout/__init__.py
kaikout/__main__.py
kaikout/about.py
kaikout/config.py
kaikout/database.py
kaikout/log.py
kaikout/utilities.py
kaikout/version.py
kaikout/assets/about.toml
kaikout/assets/blocklist.toml
kaikout/assets/commands.toml
kaikout/assets/rtbl.toml
kaikout/assets/settings.toml
kaikout/configs/accounts.toml
kaikout/configs/bookmarks.toml
kaikout/xmpp/adhoc.py
kaikout/xmpp/chat.py
kaikout/xmpp/client.py
kaikout/xmpp/commands.py
kaikout/xmpp/dataforms.py
kaikout/xmpp/events.py
kaikout/xmpp/forms.py
kaikout/xmpp/groupchat.py
kaikout/xmpp/message.py
kaikout/xmpp/moderation.py
kaikout/xmpp/muc.py
kaikout/xmpp/observation.py
kaikout/xmpp/presence.py
kaikout/xmpp/profile.py
kaikout/xmpp/pubsub.py
kaikout/xmpp/status.py
kaikout/xmpp/utilities.py
kaikout-0.1.dist-info/licenses/LICENSE
kaikout-0.1.dist-info/METADATA
kaikout-0.1.dist-info/WHEEL
kaikout-0.1.dist-info/entry_points.txt
kaikout-0.1.dist-info/top_level.txt
kaikout-0.1.dist-info/RECORD
