Metadata-Version: 2.4
Name: kaikout
Version: 0.1
Summary: Kaiko (Japanese: 懐古) Out is a group chat moderation chat bot
Author-email: Schimon Zachary <sch@fedora.email>
License: AGPL-3.0-only
Project-URL: Homepage, https://git.xmpp-it.net/sch/kaikout
Project-URL: Repository, https://git.xmpp-it.net/sch/kaikout
Keywords: bot,chat,im,jabber,spam,xmpp
Platform: any
Classifier: Intended Audience :: End Users/Desktop
Classifier: License :: OSI Approved :: GNU Affero General Public License v3
Classifier: Natural Language :: English
Classifier: Programming Language :: Python
Classifier: Programming Language :: Python :: 3.10
Classifier: Topic :: Communications :: Chat
Classifier: Topic :: Internet :: XMPP
License-File: LICENSE
Requires-Dist: tomli
Requires-Dist: tomli_w
Requires-Dist: slixmpp
Dynamic: license-file
